stock_stil/__init__.py
stock_stil/comments/__init__.py
stock_stil/comments/eastmoney.py
stock_stil/utils/__init__.py
stock_stil/utils/file_utils.py
stock_stil-0.1.6.dist-info/LICENSE
stock_stil-0.1.6.dist-info/METADATA
stock_stil-0.1.6.dist-info/WHEEL
stock_stil-0.1.6.dist-info/RECORD
